nightshifttrader/__init__.py
nightshifttrader/stock_fetcher.py
nightshifttrader-0.1.0.dist-info/LICENSE
nightshifttrader-0.1.0.dist-info/METADATA
nightshifttrader-0.1.0.dist-info/WHEEL
nightshifttrader-0.1.0.dist-info/top_level.txt
nightshifttrader-0.1.0.dist-info/RECORD
