Metadata-Version: 2.1
Name: nightshifttrader
Version: 0.1.0
Summary: A simple package to fetch stock prices
Home-page: https://github.com/nightshiftt/nightshifttrader
Author: Your Name
Author-email: nightshiftdevv@gmail.com
Classifier: Programming Language :: Python :: 3
Classifier: License :: OSI Approved :: MIT License
Classifier: Operating System :: OS Independent
License-File: LICENSE
Requires-Dist: requests
